rlay/__init__.py
rlay/core.py
rlay/mmap_backends.py
rlay/mmap_envs.py
rlay/py.typed
rlay/utils.py
rlay/gym_grpc/__init__.py
rlay/gym_grpc/gym_rlay_pb2.py
rlay/gym_grpc/gym_rlay_pb2.pyi
rlay-0.0.1.dist-info/METADATA
rlay-0.0.1.dist-info/WHEEL
rlay-0.0.1.dist-info/licenses/LICENSE
rlay-0.0.1.dist-info/RECORD
