Metadata-Version: 2.1
Name: rlay
Version: 0.0.1
Summary: A new Farama library
Project-URL: Homepage, https://farama.org
Project-URL: Repository, https://github.com/Farama-Foundation/rlay
Project-URL: Documentation, https://rlay.farama.org
Project-URL: Bug Report, https://github.com/Farama-Foundation/rlay/issues
Author-email: Farama Foundation <contact@farama.org>
License: MIT License
License-File: LICENSE
Keywords: AI,RL,Reinforcement Learning,game,rlay
Classifier: Development Status :: 4 - Beta
Classifier: Intended Audience :: Science/Research
Classifier: License :: OSI Approved :: MIT License
Classifier: Programming Language :: Python :: 3
Classifier: Programming Language :: Python :: 3.8
Classifier: Programming Language :: Python :: 3.9
Classifier: Programming Language :: Python :: 3.10
Classifier: Programming Language :: Python :: 3.11
Classifier: Programming Language :: Python :: 3.12
Classifier: Topic :: Scientific/Engineering :: Artificial Intelligence
Requires-Python: >=3.8
Requires-Dist: grpcio-tools~=1.60.0
Requires-Dist: grpcio~=1.60.0
Requires-Dist: gymnasium>=0.29.1
Requires-Dist: numpy>=1.21.0
Requires-Dist: tqdm~=4.64.1
Provides-Extra: all
Provides-Extra: testing
Requires-Dist: pytest==7.1.3; extra == 'testing'
